configurator/__init__.py
configurator/_toml.py
configurator/config.py
configurator/mapping.py
configurator/merge.py
configurator/node.py
configurator/parsers.py
configurator/path.py
configurator/patterns.py
configurator-3.2.0.dist-info/LICENSE.txt
configurator-3.2.0.dist-info/METADATA
configurator-3.2.0.dist-info/WHEEL
configurator-3.2.0.dist-info/top_level.txt
configurator-3.2.0.dist-info/RECORD
