Metadata-Version: 2.1
Name: configurator
Version: 3.2.0
Summary: A library for building a configuration store from one or more layered configuration sources
Home-page: https://github.com/Simplistix/configurator
Author: Chris Withers
Author-email: chris@withers.org
License: MIT
Classifier: Intended Audience :: Developers
Classifier: License :: OSI Approved :: MIT License
Classifier: Programming Language :: Python :: 3
Requires-Python: >=3.6
License-File: LICENSE.txt
Provides-Extra: build
Requires-Dist: sphinx ; extra == 'build'
Requires-Dist: furo ; extra == 'build'
Requires-Dist: setuptools-git ; extra == 'build'
Requires-Dist: twine ; extra == 'build'
Requires-Dist: wheel ; extra == 'build'
Provides-Extra: test
Requires-Dist: jinja2 ; extra == 'test'
Requires-Dist: mock ; extra == 'test'
Requires-Dist: pyfakefs ; extra == 'test'
Requires-Dist: pytest ; extra == 'test'
Requires-Dist: pytest-cov ; extra == 'test'
Requires-Dist: requests ; extra == 'test'
Requires-Dist: sybil ; extra == 'test'
Requires-Dist: testfixtures ; extra == 'test'
Requires-Dist: voluptuous ; extra == 'test'
Provides-Extra: toml
Requires-Dist: tomli ; (python_version < "3.11") and extra == 'toml'
Provides-Extra: yaml
Requires-Dist: pyyaml ; extra == 'yaml'
